orca/__init__.py
orca/core.py
orcasqls-1.0.0.dist-info/METADATA
orcasqls-1.0.0.dist-info/WHEEL
orcasqls-1.0.0.dist-info/top_level.txt
orcasqls-1.0.0.dist-info/RECORD
