Metadata-Version: 2.4
Name: orcasqls
Version: 1.0.0
Summary: Prints Oracle SQL/PLSQL code from DBMS lab record for study & practice
Author: Δrj★n
Keywords: oracle sql plsql study lab dbms education
Classifier: Programming Language :: Python :: 3
Classifier: License :: OSI Approved :: MIT License
Classifier: Operating System :: OS Independent
Classifier: Topic :: Education
Classifier: Topic :: Database
Classifier: Intended Audience :: Education
Requires-Python: >=3.7
Dynamic: author
Dynamic: classifier
Dynamic: description
Dynamic: description-content-type
Dynamic: keywords
Dynamic: requires-python
Dynamic: summary
